tweetlib/__init__.py
tweetlib/tweetlib.py
tweetlib-0.2.0.dist-info/LICENSE
tweetlib-0.2.0.dist-info/METADATA
tweetlib-0.2.0.dist-info/WHEEL
tweetlib-0.2.0.dist-info/top_level.txt
tweetlib-0.2.0.dist-info/RECORD
