Metadata-Version: 2.1
Name: tweetlib
Version: 0.2.0
Summary: A python twitter scraper with no-api keys required.
Home-page: https://github.com/wyattferguson/tweetlib
Author: Wyatt Ferguson
Author-email: wyattf@gmail.com
License: UNKNOWN
Platform: UNKNOWN
Classifier: Programming Language :: Python :: 3
Classifier: License :: OSI Approved :: MIT License
Classifier: Operating System :: OS Independent
